kipoi/__init__.py
kipoi/__main__.py
kipoi/_version.py
kipoi/components.py
kipoi/config.py
kipoi/data.py
kipoi/data_utils.py
kipoi/env_db.py
kipoi/logging.conf
kipoi/metadata.py
kipoi/model.py
kipoi/pipeline.py
kipoi/plugin.py
kipoi/readers.py
kipoi/remote.py
kipoi/sources.py
kipoi/specs.py
kipoi/utils.py
kipoi/writers.py
kipoi/cli/__init__.py
kipoi/cli/env.py
kipoi/cli/main.py
kipoi/cli/parser_utils.py
kipoi/cli/singularity.py
kipoi/cli/source_test.py
kipoi/external/__init__.py
kipoi/external/related/__init__.py
kipoi/external/related/fields.py
kipoi/external/related/mixins.py
kipoi/external/torchvision/__init__.py
kipoi/external/torchvision/dataset_utils.py
kipoi/model_template/README.md
kipoi/model_template/cookiecutter.json
kipoi/model_template/hooks/pre_gen_project.py
kipoi/model_template/{{cookiecutter.model_name}}/LICENSE
kipoi/model_template/{{cookiecutter.model_name}}/dataloader.py
kipoi/model_template/{{cookiecutter.model_name}}/dataloader.yaml
kipoi/model_template/{{cookiecutter.model_name}}/model.yaml
kipoi/model_template/{{cookiecutter.model_name}}/readme.md
kipoi/model_template/{{cookiecutter.model_name}}/{% if cookiecutter.model_type == 'custom' %}model.py{% endif %}
kipoi/model_template/{{cookiecutter.model_name}}/dataloader_files/x_transformer.pkl
kipoi/model_template/{{cookiecutter.model_name}}/dataloader_files/y_transformer.pkl
kipoi/model_template/{{cookiecutter.model_name}}/example_files/features.csv
kipoi/model_template/{{cookiecutter.model_name}}/example_files/targets.csv
kipoi/model_template/{{cookiecutter.model_name}}/model_files/model.json
kipoi/model_template/{{cookiecutter.model_name}}/model_files/model.pkl
kipoi/model_template/{{cookiecutter.model_name}}/model_files/weights.h5
kipoi/model_template/{{cookiecutter.model_name}}/model_files/weights.json
kipoi-0.8.6.dist-info/LICENSE
kipoi-0.8.6.dist-info/METADATA
kipoi-0.8.6.dist-info/WHEEL
kipoi-0.8.6.dist-info/entry_points.txt
kipoi-0.8.6.dist-info/top_level.txt
kipoi-0.8.6.dist-info/RECORD
