Metadata-Version: 2.1
Name: kipoi
Version: 0.8.6
Summary: Kipoi: model zoo for genomics
Home-page: https://github.com/kipoi/kipoi
Author: Kipoi team
Author-email: avsec@in.tum.de
License: MIT license
Keywords: model zoo,deep learning,computational biology,bioinformatics,genomics
License-File: LICENSE
Requires-Dist: pyyaml
Requires-Dist: numpy
Requires-Dist: pandas (>=0.21.0)
Requires-Dist: tqdm
Requires-Dist: related (>=0.6.0)
Requires-Dist: colorlog
Requires-Dist: jinja2
Requires-Dist: cookiecutter (>=1.6.0)
Requires-Dist: h5py
Requires-Dist: urllib3 (>=1.21.1)
Requires-Dist: tinydb
Requires-Dist: kipoi-utils (>=0.7.5)
Requires-Dist: kipoi-conda (>=0.1.6)
Requires-Dist: deprecation (>=2.0.6)
Requires-Dist: attrs (<=21.4.0)
Provides-Extra: develop
Requires-Dist: bump2version ; extra == 'develop'
Requires-Dist: gitpython ; extra == 'develop'
Requires-Dist: wheel ; extra == 'develop'
Requires-Dist: jedi ; extra == 'develop'
Requires-Dist: epc ; extra == 'develop'
Requires-Dist: pyarrow ; extra == 'develop'
Requires-Dist: pytest (>=3.3.1) ; extra == 'develop'
Requires-Dist: pytest-xdist ; extra == 'develop'
Requires-Dist: pytest-pep8 ; extra == 'develop'
Requires-Dist: pytest-cov ; extra == 'develop'
Requires-Dist: scikit-learn ; extra == 'develop'
Requires-Dist: cython ; extra == 'develop'
Requires-Dist: keras ; extra == 'develop'
Requires-Dist: tensorflow ; extra == 'develop'
Requires-Dist: zarr (>=2.2.0) ; extra == 'develop'
Requires-Dist: kipoi-interpret (>=0.1.2) ; extra == 'develop'
Requires-Dist: concise (>=0.6.6) ; extra == 'develop'
